qrcx/__init__.py
qrcx/qrcx.py
qrcx-0.1.dist-info/METADATA
qrcx-0.1.dist-info/WHEEL
qrcx-0.1.dist-info/entry_points.txt
qrcx-0.1.dist-info/top_level.txt
qrcx-0.1.dist-info/RECORD
