Metadata-Version: 2.4
Name: QRCX
Version: 0.1
Summary: Advanced QR Code Generator Tool (QRCX)
Author: Babar Ali Jamali
Author-email: babar995@gmail.com
Requires-Python: >=3.6
Requires-Dist: qrcode
Requires-Dist: fpdf
Dynamic: author
Dynamic: author-email
Dynamic: requires-dist
Dynamic: requires-python
Dynamic: summary
